{"errors":[],"warnings":[],"namedChunkGroups":{"app":{"chunks":[4,0,2,1],"assets":["webpack-runtime-6dfe4b6db0e2e9b4d911.js","webpack-runtime-6dfe4b6db0e2e9b4d911.js.map","styles.91711055515e1762de9e.css","styles-ab4ed2986caa553e1895.js","styles-ab4ed2986caa553e1895.js.map","commons-64463b2799a2deb662bc.js","commons-64463b2799a2deb662bc.js.map","app-4c5602a932f6c79fb580.js","app-4c5602a932f6c79fb580.js.map"],"children":{},"childAssets":{}},"component---src-pages-index-js":{"chunks":[0,3],"assets":["styles.91711055515e1762de9e.css","styles-ab4ed2986caa553e1895.js","styles-ab4ed2986caa553e1895.js.map","component---src-pages-index-js-56919c3a38bfefc3870f.js","component---src-pages-index-js-56919c3a38bfefc3870f.js.map"],"children":{},"childAssets":{}}},"assetsByChunkName":{"app":["webpack-runtime-6dfe4b6db0e2e9b4d911.js","styles.91711055515e1762de9e.css","styles-ab4ed2986caa553e1895.js","commons-64463b2799a2deb662bc.js","app-4c5602a932f6c79fb580.js"],"component---src-pages-index-js":["styles.91711055515e1762de9e.css","styles-ab4ed2986caa553e1895.js","component---src-pages-index-js-56919c3a38bfefc3870f.js"]}}